wait4localstack/VERSION
wait4localstack/__init__.py
wait4localstack/localstack.py
wait4localstack/service.py
wait4localstack-1.0.1.dist-info/LICENSE
wait4localstack-1.0.1.dist-info/METADATA
wait4localstack-1.0.1.dist-info/WHEEL
wait4localstack-1.0.1.dist-info/entry_points.txt
wait4localstack-1.0.1.dist-info/top_level.txt
wait4localstack-1.0.1.dist-info/RECORD
