Metadata-Version: 2.1
Name: wait4localstack
Version: 1.0.1
Summary: Python utilities for ensuring that localstack has fully started.
Home-page: https://github.com/locp/wait4localstack
Author: League of Crafty Programmers Ltd.
Author-email: info@locp.co.uk
Project-URL: Bug Tracker, https://github.com/locp/wait4localstack/issues
Keywords: localstack
Classifier: Programming Language :: Python :: 3
Classifier: License :: OSI Approved :: BSD License
Classifier: Operating System :: OS Independent
Requires-Python: >=3.6
License-File: LICENSE
Requires-Dist: urllib3 (>=1.26.0)
